Workbook

Sheet Instructions
A1: NUTRITION INTERNATIONAL — STAFF COST SCENARIO PLANNER
A2: Corporate Finance & Business Planning Tool · FY 2025–26
A4: PURPOSE
A5: This tool helps managers scenario-plan the true cost of hiring staff across all Nutrition International office locations.
A6: It includes three cost calculators: total annual employment cost, cost of replacing a departing employee, and cost of staff leave.
A8: WORKBOOK TABS
A9: 1. Country Data — Employer contribution rates and leave entitlements for all 11 NI locations
A10: 2. Assumptions — Shared inputs used across all calculators (edit these cells to model scenarios)
A11: 3. Employment Cost — Annual cost of employing one person: salary + mandatory contributions + benefits
A12: 4. Replacement Cost — Full cost of replacing a departing employee (recruitment, onboarding, ramp-up)
A13: 5. Leave Cost — Cost when an employee goes on maternity, medical, or extended leave
A14: 6. Compare Locations — Side-by-side comparison of all three costs across selected NI locations
... A31: Leave entitlements reflect statutory minimums; NI policies may exceed these.

Sheet Country Data
A1: COUNTRY DATA — Employer Contribution Rates & Leave Entitlements (All NI Office Locations)
A2: Country | B2: Flag | C2: Region | D2: City | E2: Currency | F2: FX Rate (1 USD =) | G2: Pension / Retirement (% salary) | H2: Health / Social (% salary) | I2: Other Mandatory (% salary) | J2: TOTAL Mandatory (%) | K2: Typical Benefits (% salary) | L2: Govt Leave Pay Subsidy (%) | M2: Maternity Leave (weeks) | N2: Annual Leave (days/yr)
A3: Canada | B3: 🇨🇦 | C3: Americas (HQ) | D3: Ottawa | E3: CAD | F3: 1.4 | G3: 5.95 | H3: 2.32 | I3: 0 | J3: 8.27 | K3: 7 | L3: 55 | M3: 17 | N3: 15
A4: Kenya | B4: 🇰🇪 | C4: Africa | D4: Nairobi | E4: KES | F4: 129.9 | G4: 2 | H4: 6.25 | I4: 0 | J4: 8.25 | K4: 4 | L4: 0 | M4: 13 | N4: 21
A5: Ethiopia | B5: 🇪🇹 | C5: Africa | D5: Addis Ababa | E5: ETB | F5: 113.6 | G5: 11 | H5: 0 | I5: 0 | J5: 11 | K5: 3 | L5: 0 | M5: 13 | N5: 16
A6: Nigeria | B6: 🇳🇬 | C6: Africa | D6: Abuja | E6: NGN | F6: 1538.5 | G6: 10 | H6: 0 | I6: 2 | J6: 12 | K6: 4.5 | L6: 0 | M6: 12 | N6: 21
A7: Senegal | B7: 🇸🇳 | C7: Africa (Sahel) | D7: Dakar | E7: XOF | F7: 613.5 | G7: 14 | H7: 7 | I7: 12 | J7: 33 | K7: 3 | L7: 0 | M7: 14 | N7: 24
A8: Tanzania | B8: 🇹🇿 | C8: Africa | D8: Dar es Salaam | E8: TZS | F8: 2564.1 | G8: 10 | H8: 0 | I8: 4.5 | J8: 14.5 | K8: 3.5 | L8: 0 | M8: 13 | N8: 28
A9: India | B9: 🇮🇳 | C9: Asia (Regional HQ) | D9: New Delhi | E9: INR | F9: 83.3 | G9: 12 | H9: 3.25 | I9: 4.81 | J9: 20.06 | K9: 3.5 | L9: 0 | M9: 26 | N9: 15
A10: Bangladesh | B10: 🇧🇩 | C10: Asia | D10: Dhaka | E10: BDT | F10: 109.9 | G10: 10 | H10: 0 | I10: 4.17 | J10: 14.17 | K10: 2.5 | L10: 0 | M10: 16 | N10: 10
A11: Indonesia | B11: 🇮🇩 | C11: Asia | D11: Jakarta | E11: IDR | F11: 16129 | G11: 3.7 | H11: 4 | I11: 3.1 | J11: 10.8 | K11: 3 | L11: 0 | M11: 13 | N11: 12
A12: Pakistan | B12: 🇵🇰 | C12: Asia | D12: Islamabad | E12: PKR | F12: 277.8 | G12: 5 | H12: 6 | I12: 0 | J12: 11 | K12: 3 | L12: 0 | M12: 12 | N12: 14
A13: Philippines | B13: 🇵🇭 | C13: Asia | D13: Manila | E13: PHP | F13: 55.6 | G13: 9.5 | H13: 2.5 | I13: 2 | J13: 14 | K13: 3.5 | L13: 80 | M13: 11 | N13: 5
A14: Sources: PwC Worldwide Tax Summaries (2025) · ISSA Country Profiles · National statutory authorities. Rates are indicative — verify before submission.

Sheet Assumptions
A1: SCENARIO ASSUMPTIONS — Edit blue/yellow cells to model different scenarios
A2: A. POSITION DETAILS
A3: Job Title | B3: Program Officer | C3: text | D3: For reference only
A4: Seniority Level | B4: Mid-Level (3-7 yrs) | C4: text | D4: Junior / Mid-Level / Senior / Director
A5: Annual Base Salary | B5: 45000 | C5: USD equivalent | D5: Enter in USD. FX conversion shown on Country Data tab.
A6: Contract Type | B6: Permanent | C6: text | D6: Permanent / Fixed-Term / Consultant
A8: B. RECRUITMENT ASSUMPTIONS
A9: Recruitment Agency Fee | B9: 0.18 | C9: % of annual salary | D9: Typical range: 12–25%. Use 0% for direct/internal recruitment.
A10: Job Advertising Cost | B10: 400 | C10: USD | D10: Job boards, LinkedIn, local postings
A11: Total Interview Hours (panel) | B11: 18 | C11: hours | D11: Total interviewer-hours across all rounds
A12: Onboarding & Training Cost | B12: 2000 | C12: USD | D12: Materials, induction time, IT setup
A13: Ramp-up Period | B13: 3 | C13: months | D13: Time until new hire reaches full productivity
A14: Productivity During Ramp-up | B14: 0.55 | C14: % of full output | D14: Typical range: 40–70%
A15: Knowledge & Handover Loss | B15: 0.1 | C15: % of annual salary | D15: Institutional knowledge, client relationships, documentation
A17: C. LEAVE ASSUMPTIONS
A18: Temp / Backfill Daily Rate | B18: 200 | C18: USD/day | D18: Daily cost of temporary cover or backfill person
A19: Maternity Leave Duration (scenario) | B19: 17 | C19: weeks | D19: Override statutory minimum if NI policy is more generous
A20: Medical Leave Duration (scenario) | B20: 4 | C20: weeks | D20: Duration for the leave cost scenario
A21: Employer Continues Full Salary? | B21: Yes | C21: Yes/Partial/No | D21: Yes = employer bears full salary; No = statutory benefit only
A22: Team Productivity Impact | B22: 0.12 | C22: % of leave salary | D22: Overhead from covering duties, knowledge gaps, re-training
A25: 📂 2026 SALARY STRUCTURES ON SHAREPOINT
A26: People & Culture SharePoint › Total Rewards › Employee Compensation › 2025 Salary Admin › Jan 2026 Salary Structures .xlsx
A27: URL: https://nutritionintl.sharepoint.com/sites/M365_PeopleandCulture/Shared Documents/Total Rewards/Employee Compensation/2025 Salary Admin/Jan 2026 Salary Structures .xlsx

Sheet Employment Cost
A1: ANNUAL EMPLOYMENT COST CALCULATOR
A2: Select Location: | C2: Canada | D2: ← Select country. Salary & assumptions from the Assumptions tab.
A4: POSITION DETAILS
A5: Job Title | C5: =Assumptions!B3 -> Program Officer
A6: Seniority | C6: =Assumptions!B4 -> Mid-Level (3-7 yrs)
A7: Annual Base Salary | C7: =Assumptions!B5 -> 45000
A8: Contract Type | C8: =Assumptions!B6 -> Permanent
A9: Selected Country | C9: =C2 -> Canada
A10: Country Region | C10: =IFERROR(VLOOKUP(C2,'Country Data'!$A$3:$N$13,3,0),"-") -> Americas (HQ)
A11: Office City | C11: =IFERROR(VLOOKUP(C2,'Country Data'!$A$3:$N$13,4,0),"-") -> Ottawa
A12: Local Currency | C12: =IFERROR(VLOOKUP(C2,'Country Data'!$A$3:$N$13,5,0),"-") -> CAD
A13: Indicative FX Rate | C13: =IFERROR(VLOOKUP(C2,'Country Data'!$A$3:$N$13,6,0),"-") -> 1.4
A15: ANNUAL COST BREAKDOWN
A16: Base Annual Salary | C16: =Assumptions!B5 -> 45000
A17: Mandatory Contributions (% of salary) | C17: =IFERROR(VLOOKUP(C2,'Country Data'!$A$3:$N$13,10,0),0) -> 8.27
A18: Mandatory Contributions (USD) | C18: =C16*C17 -> 372150
A19: Employer Benefits % (est.) | C19: =IFERROR(VLOOKUP(C2,'Country Data'!$A$3:$N$13,11,0),0) -> 7
A20: Employer Benefits (USD) | C20: =C16*C19 -> 315000
A21: Total Employer On-Cost Burden % | C21: =(C18+C20)/C16 -> 15.27
A22: TOTAL ANNUAL EMPLOYMENT COST (USD) | C22: =C16+C18+C20 -> 732150
A24: CONTRIBUTION DETAIL BY SCHEME
A25: Pension / Retirement Contribution % | C25: =IFERROR(VLOOKUP(C2,'Country Data'!$A$3:$N$13,7,0),0) -> 5.95
A26: Pension / Retirement (USD/yr) | C26: =C16*C25 -> 267750
A27: Health / Social Insurance % | C27: =IFERROR(VLOOKUP(C2,'Country Data'!$A$3:$N$13,8,0),0) -> 2.32
A28: Health / Social Insurance (USD/yr) | C28: =C16*C27 -> 104400
A29: Other Mandatory Contributions % | C29: =IFERROR(VLOOKUP(C2,'Country Data'!$A$3:$N$13,9,0),0) -> 0
A30: Other Mandatory Contributions (USD/yr) | C30: =C16*C29 -> 0
A31: Employer Benefits (health, life, etc.) | C31: =C20 -> 315000
A32: Govt Leave Pay Subsidy (maternity) | C32: =IFERROR(VLOOKUP(C2,'Country Data'!$A$3:$N$13,12,0),0) -> 55
A34: LOCAL CURRENCY EQUIVALENT
A35: Total Employment Cost in Local Currency | C35: =IFERROR(C22*VLOOKUP(C2,'Country Data'!$A$3:$N$13,6,0),"-") -> 1025010
A36: Monthly Cost in Local Currency | C36: =IFERROR(C35/12,"-") -> 85417.5

Sheet Replacement Cost
A1: EMPLOYEE REPLACEMENT COST CALCULATOR
A2: Select Location: | C2: Canada | D2: ← Salary & assumptions from Assumptions tab | H2: Country | I2: BG Check $
H3: Canada | I3: 220
A4: REPLACEMENT COST BREAKDOWN | H4: Kenya | I4: 70
A5: Base Annual Salary (from Assumptions) | C5: =Assumptions!B5 -> 45000 | H5: Ethiopia | I5: 55
A6: Daily Rate (salary / 260 working days) | C6: =Assumptions!B5/260 -> 173.07692 | H6: Nigeria | I6: 65
H7: Senegal | I7: 65
A8: 1. Recruitment Agency / Search Fee | C8: =Assumptions!B5*Assumptions!B9 -> 8100 | H8: Tanzania | I8: 65
A9: 2. Job Advertising & Posting | C9: =Assumptions!B10 -> 400 | H9: India | I9: 90
A10: 3. Interview Panel Time Cost | C10: =(Assumptions!B5/260)*Assumptions!B11/8 -> 389.42308 | H10: Bangladesh | I10: 70
A11: 4. Background & Reference Checks | C11: =IFERROR(VLOOKUP(C2,$H$3:$I$13,2,0),100) -> 220 | H11: Indonesia | I11: 80
A12: 5. Onboarding & Training | C12: =Assumptions!B12 -> 2000 | H12: Pakistan | I12: 70
A13: 6. Productivity Loss During Ramp-up | C13: =Assumptions!B5*(Assumptions!B13/12)*(1-Assumptions!B14) -> 5062.5 | H13: Philippines | I13: 80
A14: 7. Knowledge & Handover Loss | C14: =Assumptions!B5*Assumptions!B15 -> 4500
A15: TOTAL REPLACEMENT COST (USD) | C15: =C8+C9+C10+C11+C12+C13+C14 -> 20671.923
A16: As % of Annual Base Salary | C16: =IFERROR(C15/C5,0) -> 0.45937607
A18: ESTIMATED REPLACEMENT TIMELINE
A19: Vacancy / Active Recruitment Period | C19: ~8 weeks (assumption)
A20: Notice & Handover Period | C20: =IFERROR(VLOOKUP(C2,'Country Data'!$A$3:$N$13,0,0),30)&" days statutory" -> 30 days statutory
A21: Onboarding & Ramp-up Period | C21: =ROUND(Assumptions!B13*4.33,0)&" weeks" -> 13 weeks
A22: TOTAL: Weeks to Full Productivity | C22: =ROUND(8 + 8 + Assumptions!B13*4.33, 0)&" weeks (est.)" -> 29 weeks (est.)

Sheet Leave Cost
A1: STAFF LEAVE COST CALCULATOR
A2: Select Location: | C2: Canada
A3: Leave Type: | C3: Maternity / Parental
A4: Leave Duration (weeks): | C4: 17
A5: Backfill Required? | C5: Full backfill (hire temp)
A7: LEAVE COST BREAKDOWN
A8: Annual Base Salary (from Assumptions) | C8: =Assumptions!B5 -> 45000
A9: Weekly Salary | C9: =Assumptions!B5/52 -> 865.38462
A10: Gross Salary During Leave | C10: =(Assumptions!B5/52)*C4 -> 14711.538
A11: Less: Government / Statutory Leave Pay | C11: =-IFERROR((Assumptions!B5/52)*C4*VLOOKUP(C2,'Country Data'!$A$3:$N$13,12,0)/100,0) -> -8091.3462
A12: Net Salary Cost to Employer | C12: =C10+C11 -> 6620.1923
A13: Employer Contributions on Salary Paid | C13: =IFERROR(C12*VLOOKUP(C2,'Country Data'!$A$3:$N$13,10,0)/100,0) -> 547.4899
A14: Backfill / Temporary Cover Cost | C14: =IF(C5="Full backfill (hire temp)",Assumptions!B18*C4*5,IF(C5="Partial redistribution (40%)",Assumptions!B18*C4*5*0.4,0)) -> 17000
A15: Team Productivity Impact (est.) | C15: =(Assumptions!B5/52)*C4*Assumptions!B22 -> 1765.3846
A16: Admin & Transition Overhead | C16: =450 -> 450
A17: TOTAL LEAVE COST TO ORGANISATION (USD) | C17: =SUM(C12:C16) -> 26383.067
A19: STATUTORY LEAVE ENTITLEMENTS — SELECTED COUNTRY
A20: Maternity Leave (statutory) | C20: =IFERROR(VLOOKUP(C2,'Country Data'!$A$3:$N$13,13,0),"—")&" weeks" -> 17 weeks
A21: Annual Leave (statutory) | C21: =IFERROR(VLOOKUP(C2,'Country Data'!$A$3:$N$13,14,0),"—")&" working days/yr" -> 15 working days/yr
A22: Govt Leave Pay Subsidy | C22: =IFERROR(IF(VLOOKUP(C2,'Country Data'!$A$3:$N$13,12,0)=0,"None — employer bears full cost",VLOOKUP(C2,'Country Data'!$A$3:$N$13,12,0)&"% of salary covered by govt"),"—") -> 55% of salary covered by govt
A23: Total Mandatory Employer Rate | C23: =IFERROR(VLOOKUP(C2,'Country Data'!$A$3:$N$13,10,0),0) -> 8.27

Sheet Compare Locations
A1: LOCATION COST COMPARISON — SIDE BY SIDE (UP TO 4 LOCATIONS)
A2: Base Salary (USD): | C2: =Assumptions!B5 -> 45000 | D2: ← Pulling from Assumptions tab. Change salary there to update all columns.
A3: Cost Component
C4: Canada | D4: Kenya | E4: India | F4: Nigeria
A5: SECTION 1 — ANNUAL EMPLOYMENT COST
A6: Base Annual Salary (USD) | C6: =Assumptions!$B$5 -> 45000 | D6: =Assumptions!$B$5 -> 45000 | E6: =Assumptions!$B$5 -> 45000 | F6: =Assumptions!$B$5 -> 45000
A7: Mandatory Employer Contributions (%) | C7: =IFERROR(VLOOKUP(C4,'Country Data'!$A$3:$N$13,10,0),0) -> 8.27 | D7: =IFERROR(VLOOKUP(D4,'Country Data'!$A$3:$N$13,10,0),0) -> 8.25 | E7: =IFERROR(VLOOKUP(E4,'Country Data'!$A$3:$N$13,10,0),0) -> 20.06 | F7: =IFERROR(VLOOKUP(F4,'Country Data'!$A$3:$N$13,10,0),0) -> 12
A8: Mandatory Contributions (USD) | C8: =Assumptions!$B$5*IFERROR(VLOOKUP(C$4,'Country Data'!$A$3:$N$13,10,0),0) -> 372150 | D8: =Assumptions!$B$5*IFERROR(VLOOKUP(D$4,'Country Data'!$A$3:$N$13,10,0),0) -> 371250 | E8: =Assumptions!$B$5*IFERROR(VLOOKUP(E$4,'Country Data'!$A$3:$N$13,10,0),0) -> 902700 | F8: =Assumptions!$B$5*IFERROR(VLOOKUP(F$4,'Country Data'!$A$3:$N$13,10,0),0) -> 540000
A9: Employer Benefits — Health, Life (USD) | C9: =Assumptions!$B$5*IFERROR(VLOOKUP(C$4,'Country Data'!$A$3:$N$13,11,0),0) -> 315000 | D9: =Assumptions!$B$5*IFERROR(VLOOKUP(D$4,'Country Data'!$A$3:$N$13,11,0),0) -> 180000 | E9: =Assumptions!$B$5*IFERROR(VLOOKUP(E$4,'Country Data'!$A$3:$N$13,11,0),0) -> 157500 | F9: =Assumptions!$B$5*IFERROR(VLOOKUP(F$4,'Country Data'!$A$3:$N$13,11,0),0) -> 202500
A10: TOTAL ANNUAL EMPLOYMENT COST (USD) | C10: =Assumptions!$B$5+Assumptions!$B$5*IFERROR(VLOOKUP(C$4,'Country Data'!$A$3:$N$13,10,0),0)+Assumptions!$B$5*IFERROR(VLOOKUP(C$4,'Country Data'!$A$3:$N$13,11,0),0) -> 732150 | D10: =Assumptions!$B$5+Assumptions!$B$5*IFERROR(VLOOKUP(D$4,'Country Data'!$A$3:$N$13,10,0),0)+Assumptions!$B$5*IFERROR(VLOOKUP(D$4,'Country Data'!$A$3:$N$13,11,0),0) -> 596250 | E10: =Assumptions!$B$5+Assumptions!$B$5*IFERROR(VLOOKUP(E$4,'Country Data'!$A$3:$N$13,10,0),0)+Assumptions!$B$5*IFERROR(VLOOKUP(E$4,'Country Data'!$A$3:$N$13,11,0),0) -> 1105200 | F10: =Assumptions!$B$5+Assumptions!$B$5*IFERROR(VLOOKUP(F$4,'Country Data'!$A$3:$N$13,10,0),0)+Assumptions!$B$5*IFERROR(VLOOKUP(F$4,'Country Data'!$A$3:$N$13,11,0),0) -> 787500
A11: Employer Burden % (above base salary) | C11: =IFERROR((C10-Assumptions!$B$5)/Assumptions!$B$5,0) -> 15.27 | D11: =IFERROR((D10-Assumptions!$B$5)/Assumptions!$B$5,0) -> 12.25 | E11: =IFERROR((E10-Assumptions!$B$5)/Assumptions!$B$5,0) -> 23.56 | F11: =IFERROR((F10-Assumptions!$B$5)/Assumptions!$B$5,0) -> 16.5
A13: SECTION 2 — REPLACEMENT COST (if employee departs)
A14: Recruitment (agency + ads + interviews) | C14: =Assumptions!$B$5*Assumptions!$B$9+Assumptions!$B$10+(Assumptions!$B$5/260)*Assumptions!$B$11/8 -> 8889.4231 | D14: =Assumptions!$B$5*Assumptions!$B$9+Assumptions!$B$10+(Assumptions!$B$5/260)*Assumptions!$B$11/8 -> 8889.4231 | E14: =Assumptions!$B$5*Assumptions!$B$9+Assumptions!$B$10+(Assumptions!$B$5/260)*Assumptions!$B$11/8 -> 8889.4231 | F14: =Assumptions!$B$5*Assumptions!$B$9+Assumptions!$B$10+(Assumptions!$B$5/260)*Assumptions!$B$11/8 -> 8889.4231
A15: Background Checks (country-adjusted) | C15: =IFERROR(VLOOKUP(C$4,replacement!$h$3:$i$13,2,0),100) -> 100 | D15: =IFERROR(VLOOKUP(D$4,replacement!$h$3:$i$13,2,0),100) -> 100 | E15: =IFERROR(VLOOKUP(E$4,replacement!$h$3:$i$13,2,0),100) -> 100 | F15: =IFERROR(VLOOKUP(F$4,replacement!$h$3:$i$13,2,0),100) -> 100
A16: Onboarding & Training | C16: =Assumptions!$B$12 -> 2000 | D16: =Assumptions!$B$12 -> 2000 | E16: =Assumptions!$B$12 -> 2000 | F16: =Assumptions!$B$12 -> 2000
A17: Ramp-up Productivity Loss | C17: =Assumptions!$B$5*(Assumptions!$B$13/12)*(1-Assumptions!$B$14) -> 5062.5 | D17: =Assumptions!$B$5*(Assumptions!$B$13/12)*(1-Assumptions!$B$14) -> 5062.5 | E17: =Assumptions!$B$5*(Assumptions!$B$13/12)*(1-Assumptions!$B$14) -> 5062.5 | F17: =Assumptions!$B$5*(Assumptions!$B$13/12)*(1-Assumptions!$B$14) -> 5062.5
A18: Knowledge & Handover Loss | C18: =Assumptions!$B$5*Assumptions!$B$15 -> 4500 | D18: =Assumptions!$B$5*Assumptions!$B$15 -> 4500 | E18: =Assumptions!$B$5*Assumptions!$B$15 -> 4500 | F18: =Assumptions!$B$5*Assumptions!$B$15 -> 4500
A19: TOTAL REPLACEMENT COST (USD) | C19: =Assumptions!$B$5*Assumptions!$B$9+Assumptions!$B$10+(Assumptions!$B$5/260)*Assumptions!$B$11/8+IFERROR(VLOOKUP(C$4,replacement!$h$3:$i$13,2,0),100)+Assumptions!$B$12+Assumptions!$B$5*(Assumptions!$B$13/12)*(1-Assumptions!$B$14)+Assumptions!$B$5*Assumptions!$B$15 -> 20551.923 | D19: =Assumptions!$B$5*Assumptions!$B$9+Assumptions!$B$10+(Assumptions!$B$5/260)*Assumptions!$B$11/8+IFERROR(VLOOKUP(D$4,replacement!$h$3:$i$13,2,0),100)+Assumptions!$B$12+Assumptions!$B$5*(Assumptions!$B$13/12)*(1-Assumptions!$B$14)+Assumptions!$B$5*Assumptions!$B$15 -> 20551.923 | E19: =Assumptions!$B$5*Assumptions!$B$9+Assumptions!$B$10+(Assumptions!$B$5/260)*Assumptions!$B$11/8+IFERROR(VLOOKUP(E$4,replacement!$h$3:$i$13,2,0),100)+Assumptions!$B$12+Assumptions!$B$5*(Assumptions!$B$13/12)*(1-Assumptions!$B$14)+Assumptions!$B$5*Assumptions!$B$15 -> 20551.923 | F19: =Assumptions!$B$5*Assumptions!$B$9+Assumptions!$B$10+(Assumptions!$B$5/260)*Assumptions!$B$11/8+IFERROR(VLOOKUP(F$4,replacement!$h$3:$i$13,2,0),100)+Assumptions!$B$12+Assumptions!$B$5*(Assumptions!$B$13/12)*(1-Assumptions!$B$14)+Assumptions!$B$5*Assumptions!$B$15 -> 20551.923
A20: Replacement as % of Annual Salary | C20: =IFERROR(C19/Assumptions!$B$5,0) -> 0.4567094 | D20: =IFERROR(D19/Assumptions!$B$5,0) -> 0.4567094 | E20: =IFERROR(E19/Assumptions!$B$5,0) -> 0.4567094 | F20: =IFERROR(F19/Assumptions!$B$5,0) -> 0.4567094
A22: SECTION 3 — LEAVE COST (17 weeks maternity, full backfill)
A23: Statutory Maternity Leave (weeks) | C23: =IFERROR(VLOOKUP(C$4,'Country Data'!$A$3:$N$13,13,0),0) -> 17 | D23: =IFERROR(VLOOKUP(D$4,'Country Data'!$A$3:$N$13,13,0),0) -> 13 | E23: =IFERROR(VLOOKUP(E$4,'Country Data'!$A$3:$N$13,13,0),0) -> 26 | F23: =IFERROR(VLOOKUP(F$4,'Country Data'!$A$3:$N$13,13,0),0) -> 12
A24: Govt Leave Pay Subsidy (%) | C24: =IFERROR(VLOOKUP(C$4,'Country Data'!$A$3:$N$13,12,0),0) -> 55 | D24: =IFERROR(VLOOKUP(D$4,'Country Data'!$A$3:$N$13,12,0),0) -> 0 | E24: =IFERROR(VLOOKUP(E$4,'Country Data'!$A$3:$N$13,12,0),0) -> 0 | F24: =IFERROR(VLOOKUP(F$4,'Country Data'!$A$3:$N$13,12,0),0) -> 0
A25: Net Salary Cost to Employer (17 wks) | C25: =(Assumptions!$B$5/52)*17*(1-IFERROR(VLOOKUP(C$4,'Country Data'!$A$3:$N$13,12,0),0)/100) -> 6620.1923 | D25: =(Assumptions!$B$5/52)*17*(1-IFERROR(VLOOKUP(D$4,'Country Data'!$A$3:$N$13,12,0),0)/100) -> 14711.538 | E25: =(Assumptions!$B$5/52)*17*(1-IFERROR(VLOOKUP(E$4,'Country Data'!$A$3:$N$13,12,0),0)/100) -> 14711.538 | F25: =(Assumptions!$B$5/52)*17*(1-IFERROR(VLOOKUP(F$4,'Country Data'!$A$3:$N$13,12,0),0)/100) -> 14711.538
A26: Full Backfill Cost (temp @ daily rate) | C26: =Assumptions!$B$18*17*5 -> 17000 | D26: =Assumptions!$B$18*17*5 -> 17000 | E26: =Assumptions!$B$18*17*5 -> 17000 | F26: =Assumptions!$B$18*17*5 -> 17000
A27: TOTAL LEAVE COST — 17 wks (USD) | C27: =(Assumptions!$B$5/52)*17*(1-IFERROR(VLOOKUP(C$4,'Country Data'!$A$3:$N$13,12,0),0)/100)+Assumptions!$B$18*17*5+(Assumptions!$B$5/52)*17*Assumptions!$B$22+450 -> 25835.577 | D27: =(Assumptions!$B$5/52)*17*(1-IFERROR(VLOOKUP(D$4,'Country Data'!$A$3:$N$13,12,0),0)/100)+Assumptions!$B$18*17*5+(Assumptions!$B$5/52)*17*Assumptions!$B$22+450 -> 33926.923 | E27: =(Assumptions!$B$5/52)*17*(1-IFERROR(VLOOKUP(E$4,'Country Data'!$A$3:$N$13,12,0),0)/100)+Assumptions!$B$18*17*5+(Assumptions!$B$5/52)*17*Assumptions!$B$22+450 -> 33926.923 | F27: =(Assumptions!$B$5/52)*17*(1-IFERROR(VLOOKUP(F$4,'Country Data'!$A$3:$N$13,12,0),0)/100)+Assumptions!$B$18*17*5+(Assumptions!$B$5/52)*17*Assumptions!$B$22+450 -> 33926.923
A29: WORST CASE: Employment + Replacement Cost | C29: =IFERROR(C10+C19,0) -> 752701.92 | D29: =IFERROR(D10+D19,0) -> 616801.92 | E29: =IFERROR(E10+E19,0) -> 1125751.9 | F29: =IFERROR(F10+F19,0) -> 808051.92
A30: Additional if Leave also occurs (+17 wks) | C30: =IFERROR(C10+C19+C27,0) -> 778537.5 | D30: =IFERROR(D10+D19+D27,0) -> 650728.85 | E30: =IFERROR(E10+E19+E27,0) -> 1159678.8 | F30: =IFERROR(F10+F19+F27,0) -> 841978.85
A32: Notes: Salary pulled from Assumptions tab. Leave cost uses 17 weeks + full backfill. Recruitment uses current assumptions. Select countries using dropdown in row 4.
